gird/__init__.py
gird/common.py
gird/gird.py
gird/girdfile.py
gird/object.py
gird/rule.py
gird/rulesorter.py
gird/run.py
gird-2.1.3.dist-info/LICENSE
gird-2.1.3.dist-info/METADATA
gird-2.1.3.dist-info/WHEEL
gird-2.1.3.dist-info/entry_points.txt
gird-2.1.3.dist-info/RECORD
