Metadata-Version: 2.1
Name: gird
Version: 2.1.3
Summary: Make-like build tool & task runner for Python
Home-page: https://github.com/gird-dev/gird
License: MIT
Author: Tuukka Ruhanen
Author-email: tuukka.t.ruhanen@gmail.com
Requires-Python: >=3.9,<4.0
Classifier: License :: OSI Approved :: MIT License
Classifier: Programming Language :: Python :: 3
Classifier: Programming Language :: Python :: 3.9
Classifier: Programming Language :: Python :: 3.10
Classifier: Programming Language :: Python :: 3.11
Classifier: Programming Language :: Python :: 3.12
Classifier: Topic :: Software Development :: Build Tools
Project-URL: Repository, https://github.com/gird-dev/gird
